mubind/__init__.py
mubind/__init__.py.orig
mubind/datasets/__init__.py
mubind/datasets/datasets.py
mubind/get/__init__.py
mubind/get/get.py
mubind/models/__init__.py
mubind/models/models.py
mubind/pl/__init__.py
mubind/pl/basic.py
mubind/pl/graph.py
mubind/pl/plotting.py
mubind/pp/__init__.py
mubind/pp/prepare.py
mubind/set/__init__.py
mubind/set/set.py
mubind/tl/__init__.py
mubind/tl/aggregation.py
mubind/tl/basic.py
mubind/tl/encoding.py
mubind/tl/graph.py
mubind/tl/kmers.py
mubind/tl/loss.py
mubind/tl/prediction.py
mubind/tl/probound.py
mubind/tl/test.py
mubind-0.2.1.dist-info/LICENSE
mubind-0.2.1.dist-info/WHEEL
mubind-0.2.1.dist-info/METADATA
mubind-0.2.1.dist-info/RECORD
