Metadata-Version: 2.1
Name: mubind
Version: 0.2.1
Summary: ML for biomolecular binding
Author: Ignacio Ibarra
Maintainer-email: Ignacio Ibarra <ignacio.ibarra@helmholtz-muenchen.de>, Johanna Schneeberger <johanna.schneeberger@tum.de>
Requires-Python: >=3.9
Requires-Dist: seaborn
Requires-Dist: scikit-learn
Requires-Dist: pandas
Requires-Dist: unidecode
Requires-Dist: matplotlib
Requires-Dist: scipy
Requires-Dist: numpy>=1.22
Requires-Dist: torch
Requires-Dist: logomaker
Requires-Dist: biopython
Requires-Dist: numba
Requires-Dist: pytest
Requires-Dist: pytest-cov
Requires-Dist: openpyxl
Requires-Dist: tqdm
Requires-Dist: anndata
Requires-Dist: bump2version ; extra == "dev"
Requires-Dist: ipython ; extra == "doc"
Requires-Dist: ipywidgets>=8.0.0 ; extra == "doc"
Requires-Dist: sphinx>=5.3 ; extra == "doc"
Requires-Dist: sphinx-autodoc-annotation ; extra == "doc"
Requires-Dist: sphinx-autodoc-typehints>=1.10.3 ; extra == "doc"
Requires-Dist: sphinx-gallery ; extra == "doc"
Requires-Dist: sphinx_rtd_theme ; extra == "doc"
Requires-Dist: sphinxcontrib-bibtex>=2.3.0 ; extra == "doc"
Requires-Dist: sphinxcontrib-spelling>=7.6.2 ; extra == "doc"
Requires-Dist: nbsphinx>=0.8.1 ; extra == "doc"
Requires-Dist: myst-nb>=0.17.1 ; extra == "doc"
Requires-Dist: sphinx_copybutton>=0.5.0 ; extra == "doc"
Requires-Dist: scanpydoc ; extra == "doc"
Requires-Dist: pytest ; extra == "test"
Requires-Dist: pytest-cov ; extra == "test"
Project-URL: Documentation, https://mubind.readthedocs.io/
Project-URL: Home-page, https://github.com/theislab/mubind
Project-URL: Source, https://github.com/theislab/mubind
Provides-Extra: dev
Provides-Extra: doc
Provides-Extra: test
